{
  "name": "Monza GP",
  "segments": [
    {
      "type": "straight",
      "length": 960
    },
    {
      "type": "corner",
      "radius": 30,
      "angle": 80,
      "direction": "right"
    },
    {
      "type": "corner",
      "radius": 32,
      "angle": 70,
      "direction": "left"
    },
    {
      "type": "straight",
      "length": 300
    },
    {
      "type": "corner",
      "radius": 100,
      "angle": 75,
      "direction": "right"
    },
    {
      "type": "straight",
      "length": 760
    },
    {
      "type": "corner",
      "radius": 42,
      "angle": 70,
      "direction": "left"
    },
    {
      "type": "corner",
      "radius": 44,
      "angle": 65,
      "direction": "right"
    },
    {
      "type": "straight",
      "length": 350
    },
    {
      "type": "corner",
      "radius": 70,
      "angle": 85,
      "direction": "right"
    },
    {
      "type": "straight",
      "length": 110
    },
    {
      "type": "corner",
      "radius": 64,
      "angle": 75,
      "direction": "right"
    },
    {
      "type": "straight",
      "length": 1150
    },
    {
      "type": "corner",
      "radius": 85,
      "angle": 45,
      "direction": "left"
    },
    {
      "type": "corner",
      "radius": 78,
      "angle": 55,
      "direction": "right"
    },
    {
      "type": "corner",
      "radius": 90,
      "angle": 40,
      "direction": "left"
    },
    {
      "type": "straight",
      "length": 560
    },
    {
      "type": "corner",
      "radius": 100,
      "angle": 170,
      "direction": "right"
    },
    {
      "type": "straight",
      "length": 600
    }
  ]
}